h_ai/__init__.py
h_ai/application/__init__.py
h_ai/application/hai_service.py
h_ai/application/services/__init__.py
h_ai/application/services/base_model_service.py
h_ai/application/services/granite_service.py
h_ai/application/services/nomic_service.py
h_ai/domain/__init__.py
h_ai/domain/llm_config.py
h_ai/domain/model_factory.py
h_ai/domain/reasoning/__init__.py
h_ai/domain/reasoning/llm_chat_repository.py
h_ai/domain/reasoning/llm_embedding_repository.py
h_ai/domain/reasoning/llm_generate_respository.py
h_ai/domain/reasoning/llm_tool_repository.py
h_ai/domain/reasoning/text_analysis.py
h_ai/domain/reasoning/tool_message.py
h_ai/infrastructure/__init__.py
h_ai/infrastructure/llm/__init__.py
h_ai/infrastructure/llm/data_handler.py
h_ai/infrastructure/llm/json_resource_loader.py
h_ai/infrastructure/llm/llm_response_cleaner.py
h_ai/infrastructure/llm/prompt_helper.py
h_ai/infrastructure/llm/prompt_loader.py
h_ai/infrastructure/llm/template_loader.py
h_ai/infrastructure/llm/ollama/__init__.py
h_ai/infrastructure/llm/ollama/ollama_chat_repository.py
h_ai/infrastructure/llm/ollama/ollama_embed_repository.py
h_ai/infrastructure/llm/ollama/ollama_generate_repository.py
h_ai/infrastructure/llm/ollama/ollama_http_client.py
h_ai/infrastructure/llm/ollama/ollama_tool_repository.py
h_ai/infrastructure/llm/ollama/factories/__init__.py
h_ai/infrastructure/llm/ollama/factories/granite_factory.py
h_ai/infrastructure/llm/ollama/factories/nomic_factory.py
h_ai/infrastructure/llm/ollama/models/__init__.py
h_ai/infrastructure/llm/ollama/models/ollama_chat_message.py
h_ai/infrastructure/llm/ollama/models/ollama_chat_session.py
h_ai_brain-0.0.26.dist-info/licenses/LICENSE
h_ai_brain-0.0.26.dist-info/licenses/NOTICE.txt
h_ai_brain-0.0.26.dist-info/METADATA
h_ai_brain-0.0.26.dist-info/WHEEL
h_ai_brain-0.0.26.dist-info/top_level.txt
h_ai_brain-0.0.26.dist-info/RECORD
