Metadata-Version: 2.4
Name: h_ai_brain
Version: 0.0.26
Summary: AI Research agent API
Author-email: shoebill <shoebill.hai@gmail.com>
Classifier: Programming Language :: Python :: 3
Classifier: License :: OSI Approved :: Apache Software License
Classifier: Operating System :: OS Independent
Requires-Python: >=3.10
License-File: LICENSE
License-File: NOTICE.txt
Requires-Dist: requests~=2.32.3
Requires-Dist: jinja2~=3.1.3
Provides-Extra: dev
Requires-Dist: pytest; extra == "dev"
Dynamic: license-file
